LICENSE
assets
basicsr
colab
dist
docs
experiments
inference
options
scripts
test_scripts
tests
