Metadata-Version: 2.4
Name: animesisr-basicsr
Version: 1.0.1
Summary: Open Source Image and Video Super-Resolution Toolbox
Author-email: Xintao Wang <xintao.wang@outlook.com>
License-Expression: Apache-2.0
Project-URL: Homepage, https://github.com/TianZerL/BasicSR
Project-URL: Repository, https://github.com/TianZerL/BasicSR
Keywords: computer vision,restoration,super resolution,image processing,video processing
Classifier: Operating System :: OS Independent
Classifier: Programming Language :: Python :: 3
Classifier: Topic :: Scientific/Engineering :: Artificial Intelligence
Classifier: Topic :: Multimedia :: Graphics
Requires-Python: >=3.7
Requires-Dist: addict
Requires-Dist: future
Requires-Dist: lmdb
Requires-Dist: numpy
Requires-Dist: opencv-python
Requires-Dist: Pillow
Requires-Dist: pyyaml
Requires-Dist: requests
Requires-Dist: scikit-image
Requires-Dist: scipy
Requires-Dist: tb-nightly
Requires-Dist: torch
Requires-Dist: torchvision
Requires-Dist: tqdm
Requires-Dist: yapf
Requires-Dist: cython
